poolcop/__init__.py
poolcop/const.py
poolcop/exceptions.py
poolcop/poolcop.py
poolcop-0.0.1.dist-info/LICENSE
poolcop-0.0.1.dist-info/METADATA
poolcop-0.0.1.dist-info/WHEEL
poolcop-0.0.1.dist-info/RECORD
